{"head":{"vars":["name","item","deathDate","race","image"]},"results":{"bindings":[{"item":{"type":"uri","value":"http://www.wikidata.org/entity/Q24238427"},"name":{"xml:lang":"nl","type":"literal","value":"Bjorg Lambrecht"},"deathDate":{"datatype":"http://www.w3.org/2001/XMLSchema#dateTime","type":"literal","value":"2019-08-05T00:00:00Z"},"image":{"type":"uri","value":"http://commons.wikimedia.org/wiki/Special:FilePath/Lillers%20-%20Grand%20Prix%20de%20Lillers-Souvenir%20Bruno%20Comini%2C%206%20mars%202016%20%28B141%29.JPG"}}]}}